dragon_prep/Task001_adhesion_clf.py
dragon_prep/Task002_nodule_clf.py
dragon_prep/Task003_kidney_clf.py
dragon_prep/Task004_skin_case_selection_clf.py
dragon_prep/Task005_recist_timeline_clf.py
dragon_prep/Task006_lung_tumor_origin_clf.py
dragon_prep/Task007_nodule_diameter_presence_clf.py
dragon_prep/Task008_pdac_size_presence_clf.py
dragon_prep/Task009_pdac_diagnosis_clf.py
dragon_prep/Task010_prostate_radiology_clf.py
dragon_prep/Task011_prostate_pathology_clf.py
dragon_prep/Task012_pathology_tissue_type_clf.py
dragon_prep/Task013_pathology_tissue_origin_clf.py
dragon_prep/Task014_textual_entailment_clf.py
dragon_prep/Task015_colon_pathology_clf.py
dragon_prep/Task016_recist_lesion_size_presence_clf.py
dragon_prep/Task017_pdac_attributes_clf.py
dragon_prep/Task018_osteoarthritis_clf.py
dragon_prep/Task019_prostate_volume_reg.py
dragon_prep/Task020_psa_reg.py
dragon_prep/Task021_psad_reg.py
dragon_prep/Task022_pdac_size_reg.py
dragon_prep/Task023_nodule_diameter_reg.py
dragon_prep/Task024_recist_lesion_size_reg.py
dragon_prep/Task025_anonymisation_ner.py
dragon_prep/Task026_medical_terminology_ner.py
dragon_prep/Task027_prostate_biopsy_ner.py
dragon_prep/Task028_skin_pathology_ner.py
dragon_prep/Task101_Example_sl_bin_clf.py
dragon_prep/Task102_Example_sl_mc_clf.py
dragon_prep/Task103_Example_mednli.py
dragon_prep/Task104_Example_ml_bin_clf.py
dragon_prep/Task105_Example_ml_mc_clf.py
dragon_prep/Task106_Example_sl_reg.py
dragon_prep/Task107_Example_ml_reg.py
dragon_prep/Task108_Example_sl_ner.py
dragon_prep/Task109_Example_ml_ner.py
dragon_prep/__init__.py
dragon_prep/make_debug_splits.py
dragon_prep/mlm_zgt_radpat.py
dragon_prep/ner.py
dragon_prep/prepare_avl.py
dragon_prep/prepare_rumc.py
dragon_prep/prepare_umcg.py
dragon_prep/stats.py
dragon_prep/synthetic_data_utils.py
dragon_prep/upload_debug_datasets.py
dragon_prep/upload_debug_datasets_per_task.py
dragon_prep/upload_example_datasets.py
dragon_prep/upload_test_datasets.py
dragon_prep-0.2.9.dist-info/licenses/LICENSE
dragon_prep-0.2.9.dist-info/METADATA
dragon_prep-0.2.9.dist-info/WHEEL
dragon_prep-0.2.9.dist-info/top_level.txt
dragon_prep-0.2.9.dist-info/RECORD
