Metadata-Version: 2.4
Name: dragon_prep
Version: 0.2.9
Summary: Preprocessing scripts for the DRAGON benchmark
Home-page: https://github.com/DIAGNijmegen/dragon_prep
Author: Joeran Bosma
Author-email: Joeran.Bosma@radboudumc.nl
Project-URL: Bug Tracker, https://github.com/DIAGNijmegen/dragon_prep/issues
Platform: unix
Platform: linux
Platform: osx
Platform: cygwin
Platform: win32
Classifier: Programming Language :: Python :: 3
Classifier: Programming Language :: Python :: 3 :: Only
Classifier: Programming Language :: Python :: 3.8
Classifier: Programming Language :: Python :: 3.9
Classifier: Programming Language :: Python :: 3.10
Requires-Python: >=3.8
License-File: LICENSE
Requires-Dist: pip>=22.1.2
Requires-Dist: pandas
Requires-Dist: scikit-learn
Requires-Dist: openpyxl
Requires-Dist: spacy
Provides-Extra: testing
Requires-Dist: pytest>=6.0; extra == "testing"
Requires-Dist: pytest-cov>=2.0; extra == "testing"
Requires-Dist: mypy>=0.910; extra == "testing"
Requires-Dist: flake8>=3.9; extra == "testing"
Requires-Dist: tox>=3.24; extra == "testing"
Dynamic: author-email
Dynamic: description
Dynamic: description-content-type
Dynamic: home-page
Dynamic: license-file
Dynamic: project-url
